versioned/__init__.py
versioned/_version.py
versioned/api.py
versioned/bootstrap.py
versioned/compat.py
versioned/constants.py
versioned/dynamodb.py
versioned/exc.py
versioned/paths.py
versioned/s3_and_dynamodb_backend.py
versioned/s3_only_backend.py
versioned/utils.py
versioned/vendor/__init__.py
versioned/vendor/hashes.py
versioned/vendor/pytest_cov_helper.py
versioned-1.0.1.dist-info/AUTHORS.rst
versioned-1.0.1.dist-info/LICENSE.txt
versioned-1.0.1.dist-info/METADATA
versioned-1.0.1.dist-info/WHEEL
versioned-1.0.1.dist-info/RECORD
